{
  "sections": {
    "legal_header": {
      "type": "lt-legal-header",
      "settings": {
        "label": "Rechtliches",
        "subtitle": "",
        "show_updated_at": true,
        "updated_label": "Zuletzt aktualisiert",
        "updated_at": "24. April 2026"
      }
    },
    "main": {
      "type": "main-page",
      "settings": {
        "center": false,
        "page_cover_metafield": "",
        "color_background_main": "rgba(0,0,0,0)",
        "color_text_main": "rgba(0,0,0,0)",
        "height": "small"
      }
    }
  },
  "order": [
    "legal_header",
    "main"
  ]
}
